ntr/__init__.py
ntr/app.py
ntr/bhandar.py
nepali_to_roman-0.1.8.dist-info/LICENSE
nepali_to_roman-0.1.8.dist-info/METADATA
nepali_to_roman-0.1.8.dist-info/WHEEL
nepali_to_roman-0.1.8.dist-info/top_level.txt
nepali_to_roman-0.1.8.dist-info/RECORD
