Metadata-Version: 2.1
Name: nepali-to-roman
Version: 0.1.8
Summary: A PyPi package to convert Nepali words to Romanized English Literals. Here we perform translieration and convert Devanagari words into Roman Literals. Nepali to Roman
Home-page: https://github.com/ishparsh/Nepali-Transliteration
Author: Diwas Pandey, Ishparsh Uprety & Navraj Pokharel
Author-email: uprety.ishparsh@gmail.com
Keywords: Nepali to roman,Nepali Transliteration,devanagari to English,devanagari,Diwas Pandey,Ishparsh Uprety,Nepali to roman,Nepali words to roman,roman from nepali,convert nepali to roman,romanize nepali words,how to convert nepali to roman,convert Nepali to Roman
Classifier: Programming Language :: Python :: 3
Classifier: License :: OSI Approved :: MIT License
Classifier: Operating System :: OS Independent
Requires-Python: >=3.6
License-File: LICENSE
